{
  "modified": "Thu Apr 09 2020 16:23:50 GMT+0800 (中国标准时间)",
  "dataBindings": [
    {
      "attr": "switchState",
      "valueType": "Number",
      "name": "遥信状态"
    },
    {
      "attr": "lineColor",
      "valueType": "Color",
      "name": "颜色"
    }
  ],
  "width": 43,
  "height": 12,
  "interactive": true,
  "comps": [
    {
      "type": "shape",
      "borderWidth": 0.92429,
      "borderColor": {
        "func": "attr@lineColor",
        "value": "#0393d6"
      },
      "pixelPerfect": true,
      "points": [
        6.71143,
        9.22714,
        6.71143,
        7.95952,
        5.66834,
        6.91643,
        4.40072,
        6.91643,
        3.1331,
        6.91643,
        2.09,
        7.95952,
        2.09,
        9.22714,
        2.09,
        10.49476,
        3.1331,
        11.53786,
        4.40072,
        11.53786,
        5.66834,
        11.53786,
        6.71143,
        10.49476,
        6.71143,
        9.22714
      ],
      "segments": [
        1,
        4,
        4,
        4,
        4
      ]
    },
    {
      "type": "shape",
      "borderWidth": 0.92429,
      "borderColor": {
        "func": "attr@lineColor",
        "value": "#0393d6"
      },
      "pixelPerfect": true,
      "points": [
        40.91,
        9.22714,
        40.91,
        7.95952,
        39.8669,
        6.91643,
        38.59928,
        6.91643,
        37.33166,
        6.91643,
        36.28857,
        7.95952,
        36.28857,
        9.22714,
        36.28857,
        10.49476,
        37.33166,
        11.53786,
        38.59928,
        11.53786,
        39.8669,
        11.53786,
        40.91,
        10.49476,
        40.91,
        9.22714
      ],
      "segments": [
        1,
        4,
        4,
        4,
        4
      ]
    },
    {
      "type": "shape",
      "borderWidth": 0.92429,
      "borderColor": {
        "func": "attr@lineColor",
        "value": "#0393d6"
      },
      "dashColor": "__ht__function(data, view) {\nif (data.getAttr('switchState') === 0) {\r\n\r\n    return Math.PI / 180 * 0\r\n} else if (data.getAttr('switchState') === 1) {\r\n    console.log('打印的值>>>>')\r\n    return Math.PI / 180 * 10\r\n}\n}",
      "pixelPerfect": true,
      "anchorX": 0,
      "anchorY": 1,
      "rotation": {
        "func": "__ht__function(data, view) {\nif (data.getAttr('switchState') === 0) {\r\n    return Math.PI / 180 * 0\r\n} else if (data.getAttr('switchState') === 1) {   \r\n    return Math.PI / 180 * 10\r\n}\n}",
        "value": 0
      },
      "points": [
        39.52357,
        0.44643,
        26.43207,
        3.90113,
        6.24929,
        9.22714
      ]
    }
  ]
}